{
  "ComponentIndexes": {},
  "ControlUniqueGuids": {},
  "ControlUniqueIds": {
    "Amount_DataCard1": 130,
    "Amount_DataCard2": 58,
    "App": 1,
    "Button1": 79,
    "Button2": 136,
    "Button2_1": 135,
    "Button3": 65,
    "DataCardKey1": 102,
    "DataCardKey10": 35,
    "DataCardKey11": 40,
    "DataCardKey12": 45,
    "DataCardKey13": 50,
    "DataCardKey14": 55,
    "DataCardKey15": 60,
    "DataCardKey2": 107,
    "DataCardKey3": 112,
    "DataCardKey4": 117,
    "DataCardKey5": 122,
    "DataCardKey6": 127,
    "DataCardKey7": 132,
    "DataCardKey9": 30,
    "DataCardValue1": 103,
    "DataCardValue10": 36,
    "DataCardValue11": 41,
    "DataCardValue12": 46,
    "DataCardValue13": 51,
    "DataCardValue14": 56,
    "DataCardValue15": 61,
    "DataCardValue2": 108,
    "DataCardValue3": 113,
    "DataCardValue4": 118,
    "DataCardValue5": 123,
    "DataCardValue6": 128,
    "DataCardValue7": 133,
    "DataCardValue9": 31,
    "Description_DataCard1": 105,
    "Description_DataCard2": 33,
    "Detail": 15,
    "Dropdown1": 139,
    "Dropdown1_1": 143,
    "ErrorMessage1": 104,
    "ErrorMessage10": 37,
    "ErrorMessage11": 42,
    "ErrorMessage12": 47,
    "ErrorMessage13": 52,
    "ErrorMessage14": 57,
    "ErrorMessage15": 62,
    "ErrorMessage2": 109,
    "ErrorMessage3": 114,
    "ErrorMessage4": 119,
    "ErrorMessage5": 124,
    "ErrorMessage6": 129,
    "ErrorMessage7": 134,
    "ErrorMessage9": 32,
    "Form1": 99,
    "Form2": 27,
    "Gallery1": 83,
    "Gallery2": 6,
    "Gallery3": 73,
    "Gallery4": 22,
    "galleryTemplate1": 84,
    "galleryTemplate2": 7,
    "galleryTemplate3": 74,
    "galleryTemplate4": 23,
    "Header": 80,
    "Header_1": 137,
    "Header_2": 66,
    "Home": 67,
    "Host": 3,
    "HtmlText1": 25,
    "Icon1": 64,
    "Image7": 72,
    "Image7_1": 97,
    "Image7_2": 20,
    "Image9": 71,
    "Image9_1": 96,
    "Image9_2": 19,
    "Label1": 138,
    "Label10": 21,
    "Label2": 24,
    "Label2_2": 26,
    "Label3": 144,
    "Label4": 82,
    "Label5": 90,
    "Label6": 69,
    "Label6_1": 94,
    "Label6_2": 17,
    "Label7": 70,
    "Label7_1": 95,
    "Label7_2": 18,
    "Label8": 98,
    "New": 92,
    "NextArrow1": 86,
    "NextArrow3": 9,
    "NextArrow5": 76,
    "Note": 81,
    "Payment_Process_DataCard1": 110,
    "Payment_Process_DataCard2": 38,
    "Rectangle1": 85,
    "Rectangle3": 8,
    "Rectangle5": 75,
    "Rectangle6": 68,
    "Rectangle6_1": 93,
    "Rectangle6_2": 16,
    "Request_Case_DataCard1": 125,
    "Request_Case_DataCard2": 53,
    "Request_Status_DataCard1": 120,
    "Request_Status_DataCard2": 48,
    "Separator1": 89,
    "Separator3": 14,
    "Separator5": 78,
    "StarVisible1": 101,
    "StarVisible10": 34,
    "StarVisible11": 39,
    "StarVisible12": 44,
    "StarVisible13": 49,
    "StarVisible14": 54,
    "StarVisible15": 59,
    "StarVisible2": 106,
    "StarVisible3": 111,
    "StarVisible4": 116,
    "StarVisible5": 121,
    "StarVisible6": 126,
    "StarVisible7": 131,
    "StarVisible9": 29,
    "Status_DataCard1": 115,
    "Status_DataCard2": 43,
    "Subtitle1": 88,
    "Subtitle3": 11,
    "Subtitle3_1": 12,
    "Subtitle3_2": 13,
    "Subtitle3_3": 140,
    "Subtitle3_4": 141,
    "Subtitle3_5": 142,
    "TEST": 4,
    "TextInput1": 91,
    "TextInput2": 63,
    "TextInput3": 5,
    "Title_DataCard1": 100,
    "Title_DataCard2": 28,
    "Title1": 87,
    "Title3": 10,
    "Title5": 77
  },
  "FunctionParamsInvariantScripts": {},
  "FunctionParamsInvariantScriptsOnInstances": {},
  "HeaderLastSavedDateTimeUTC": "09/11/2023 11:19:52",
  "IsLegacyComponentAllowGlobalScopeCase": false,
  "LocalConnectionIDReferences": {
    "cefcc3df-98b2-4082-a847-a0cff2a56098": "\"/providers/microsoft.powerapps/apis/shared_sharepointonline/connections/5cfa839abf7c4946a3a42a97b16252c7\""
  },
  "LocalDatabaseReferencesAsEmpty": false,
  "LocalResourceFileNames": {
    "BKIM logo_clean": "8aca27f4-222c-4505-a988-58a34e2315d4.png",
    "BKIM logo_clean_white": "94114d1f-a349-42ef-9d8c-45e7949bae59.png"
  },
  "LocalResourceRootPaths": {
    "BKIM logo_clean": "https://docserverpwaprodeas.blob.core.windows.net/e8e56fb3-8029-441c-810a-5beeb3200848-1/resource/Assets0Images08aca27f4-222c-4505-a988-58a34e2315d4.png?sv=2018-03-28&sr=b&sig=Bd0SVVFmvV1lJ04ts0E0yTtg2LJdm7tHM3rl7H49Ylo%3D&spr=https&se=2023-09-12T03%3A36%3A07Z&sp=r",
    "BKIM logo_clean_white": "https://docserverpwaprodeas.blob.core.windows.net/e8e56fb3-8029-441c-810a-5beeb3200848-1/resource/Assets0Images094114d1f-a349-42ef-9d8c-45e7949bae59.png?sv=2018-03-28&sr=b&sig=JcD%2FOdU324jkf1k4iUAULbNY9npqyDsrvj1AEG5lfCY%3D&spr=https&se=2023-09-12T03%3A36%3A07Z&sp=r"
  },
  "OrderComponentMetadata": {},
  "OrderComponentTemplate": {},
  "OrderDataSource": {
    "3000 Records": 0,
    "BKIM_REQ_Approval_Condition": 1,
    "BKIM_REQ_Approval_Condition_Result": 2,
    "BKIM_REQ_Approval_Result": 3,
    "BKIM_REQ_Chat_List": 4,
    "BKIM_REQ_Expenditure_Approval": 5,
    "BKIM_REQ_List": 6,
    "BKIM_REQ_Payment_Approval": 7,
    "CustomGallerySample": 8,
    "DropDownSample": 9
  },
  "OrderGroupControls": {
    "Header": {
      "Image7": 2,
      "Image9": 1,
      "Label6": 3,
      "Label7": 0,
      "Rectangle6": 4
    },
    "Header_1": {
      "Image7_1": 2,
      "Image9_1": 1,
      "Label6_1": 3,
      "Label7_1": 0,
      "Rectangle6_1": 4
    },
    "Header_2": {
      "Image7_2": 2,
      "Image9_2": 1,
      "Label6_2": 3,
      "Label7_2": 0,
      "Rectangle6_2": 4
    }
  },
  "OrderPcfTemplate": {},
  "OrderTemplate": {},
  "OrderXMLTemplate": {
    "button": 9,
    "dropdown": 2,
    "form": 8,
    "gallery": 3,
    "htmlViewer": 7,
    "icon": 5,
    "image": 6,
    "label": 1,
    "rectangle": 4,
    "text": 0
  },
  "OverridablePropertiesEntry": {
    "Amount_DataCard1": {},
    "Amount_DataCard2": {},
    "App": {},
    "Button1": {},
    "Button2": {},
    "Button2_1": {},
    "Button3": {},
    "DataCardKey1": {},
    "DataCardKey10": {},
    "DataCardKey11": {},
    "DataCardKey12": {},
    "DataCardKey13": {},
    "DataCardKey14": {},
    "DataCardKey15": {},
    "DataCardKey2": {},
    "DataCardKey3": {},
    "DataCardKey4": {},
    "DataCardKey5": {},
    "DataCardKey6": {},
    "DataCardKey7": {},
    "DataCardKey9": {},
    "DataCardValue1": {},
    "DataCardValue10": {},
    "DataCardValue11": {},
    "DataCardValue12": {},
    "DataCardValue13": {},
    "DataCardValue14": {},
    "DataCardValue15": {},
    "DataCardValue2": {},
    "DataCardValue3": {},
    "DataCardValue4": {},
    "DataCardValue5": {},
    "DataCardValue6": {},
    "DataCardValue7": {},
    "DataCardValue9": {},
    "Description_DataCard1": {},
    "Description_DataCard2": {},
    "Detail": {},
    "Dropdown1": {},
    "Dropdown1_1": {},
    "ErrorMessage1": {},
    "ErrorMessage10": {},
    "ErrorMessage11": {},
    "ErrorMessage12": {},
    "ErrorMessage13": {},
    "ErrorMessage14": {},
    "ErrorMessage15": {},
    "ErrorMessage2": {},
    "ErrorMessage3": {},
    "ErrorMessage4": {},
    "ErrorMessage5": {},
    "ErrorMessage6": {},
    "ErrorMessage7": {},
    "ErrorMessage9": {},
    "Form1": {},
    "Form2": {},
    "Gallery1": {},
    "Gallery2": {},
    "Gallery3": {},
    "Gallery4": {},
    "galleryTemplate1": {},
    "galleryTemplate2": {},
    "galleryTemplate3": {},
    "galleryTemplate4": {},
    "Header": {},
    "Header_1": {},
    "Header_2": {},
    "Home": {},
    "Host": {},
    "HtmlText1": {},
    "Icon1": {},
    "Image7": {},
    "Image7_1": {},
    "Image7_2": {},
    "Image9": {},
    "Image9_1": {},
    "Image9_2": {},
    "Label1": {},
    "Label10": {},
    "Label2": {},
    "Label2_2": {},
    "Label3": {},
    "Label4": {},
    "Label5": {},
    "Label6": {},
    "Label6_1": {},
    "Label6_2": {},
    "Label7": {},
    "Label7_1": {},
    "Label7_2": {},
    "Label8": {},
    "New": {},
    "NextArrow1": {},
    "NextArrow3": {},
    "NextArrow5": {},
    "Note": {},
    "Payment_Process_DataCard1": {},
    "Payment_Process_DataCard2": {},
    "Rectangle1": {},
    "Rectangle3": {},
    "Rectangle5": {},
    "Rectangle6": {},
    "Rectangle6_1": {},
    "Rectangle6_2": {},
    "Request_Case_DataCard1": {},
    "Request_Case_DataCard2": {},
    "Request_Status_DataCard1": {},
    "Request_Status_DataCard2": {},
    "Separator1": {},
    "Separator3": {},
    "Separator5": {},
    "StarVisible1": {},
    "StarVisible10": {},
    "StarVisible11": {},
    "StarVisible12": {},
    "StarVisible13": {},
    "StarVisible14": {},
    "StarVisible15": {},
    "StarVisible2": {},
    "StarVisible3": {},
    "StarVisible4": {},
    "StarVisible5": {},
    "StarVisible6": {},
    "StarVisible7": {},
    "StarVisible9": {},
    "Status_DataCard1": {},
    "Status_DataCard2": {},
    "Subtitle1": {},
    "Subtitle3": {},
    "Subtitle3_1": {},
    "Subtitle3_2": {},
    "Subtitle3_3": {},
    "Subtitle3_4": {},
    "Subtitle3_5": {},
    "TEST": {},
    "TextInput1": {},
    "TextInput2": {},
    "TextInput3": {},
    "Title_DataCard1": {},
    "Title_DataCard2": {},
    "Title1": {},
    "Title3": {},
    "Title5": {}
  },
  "PCFDynamicSchemaForIRRetrievalEntry": {},
  "PCFTemplateEntry": {},
  "PublishOrderIndices": {
    "Amount_DataCard1": 51,
    "Amount_DataCard2": 101,
    "App": 0,
    "Button1": 12,
    "Button2": 57,
    "Button2_1": 56,
    "Button3": 108,
    "DataCardKey1": 23,
    "DataCardKey10": 78,
    "DataCardKey11": 83,
    "DataCardKey12": 88,
    "DataCardKey13": 93,
    "DataCardKey14": 98,
    "DataCardKey15": 103,
    "DataCardKey2": 28,
    "DataCardKey3": 33,
    "DataCardKey4": 38,
    "DataCardKey5": 43,
    "DataCardKey6": 48,
    "DataCardKey7": 53,
    "DataCardKey9": 73,
    "DataCardValue1": 24,
    "DataCardValue10": 79,
    "DataCardValue11": 84,
    "DataCardValue12": 89,
    "DataCardValue13": 94,
    "DataCardValue14": 99,
    "DataCardValue15": 104,
    "DataCardValue2": 29,
    "DataCardValue3": 34,
    "DataCardValue4": 39,
    "DataCardValue5": 44,
    "DataCardValue6": 49,
    "DataCardValue7": 54,
    "DataCardValue9": 74,
    "Description_DataCard1": 26,
    "Description_DataCard2": 76,
    "Detail": 0,
    "Dropdown1": 121,
    "Dropdown1_1": 123,
    "ErrorMessage1": 25,
    "ErrorMessage10": 80,
    "ErrorMessage11": 85,
    "ErrorMessage12": 90,
    "ErrorMessage13": 95,
    "ErrorMessage14": 100,
    "ErrorMessage15": 105,
    "ErrorMessage2": 30,
    "ErrorMessage3": 35,
    "ErrorMessage4": 40,
    "ErrorMessage5": 45,
    "ErrorMessage6": 50,
    "ErrorMessage7": 55,
    "ErrorMessage9": 75,
    "Form1": 20,
    "Form2": 70,
    "Gallery1": 110,
    "Gallery2": 124,
    "Gallery3": 6,
    "Gallery4": 65,
    "galleryTemplate1": 111,
    "galleryTemplate2": 125,
    "galleryTemplate3": 7,
    "galleryTemplate4": 66,
    "Header": 2,
    "Header_1": 18,
    "Header_2": 63,
    "Home": 13,
    "Host": 0,
    "HtmlText1": 68,
    "Icon1": 107,
    "Image7": 5,
    "Image7_1": 17,
    "Image7_2": 62,
    "Image9": 4,
    "Image9_1": 16,
    "Image9_2": 61,
    "Label1": 120,
    "Label10": 64,
    "Label2": 67,
    "Label2_2": 69,
    "Label3": 122,
    "Label4": 109,
    "Label5": 117,
    "Label6": 1,
    "Label6_1": 14,
    "Label6_2": 59,
    "Label7": 3,
    "Label7_1": 15,
    "Label7_2": 60,
    "Label8": 19,
    "New": 0,
    "NextArrow1": 113,
    "NextArrow3": 127,
    "NextArrow5": 9,
    "Note": 3,
    "Payment_Process_DataCard1": 31,
    "Payment_Process_DataCard2": 81,
    "Rectangle1": 112,
    "Rectangle3": 126,
    "Rectangle5": 8,
    "Rectangle6": 0,
    "Rectangle6_1": 13,
    "Rectangle6_2": 58,
    "Request_Case_DataCard1": 46,
    "Request_Case_DataCard2": 96,
    "Request_Status_DataCard1": 41,
    "Request_Status_DataCard2": 91,
    "Separator1": 116,
    "Separator3": 135,
    "Separator5": 11,
    "StarVisible1": 22,
    "StarVisible10": 77,
    "StarVisible11": 82,
    "StarVisible12": 87,
    "StarVisible13": 92,
    "StarVisible14": 97,
    "StarVisible15": 102,
    "StarVisible2": 27,
    "StarVisible3": 32,
    "StarVisible4": 37,
    "StarVisible5": 42,
    "StarVisible6": 47,
    "StarVisible7": 52,
    "StarVisible9": 72,
    "Status_DataCard1": 36,
    "Status_DataCard2": 86,
    "Subtitle1": 115,
    "Subtitle3": 129,
    "Subtitle3_1": 130,
    "Subtitle3_2": 131,
    "Subtitle3_3": 132,
    "Subtitle3_4": 133,
    "Subtitle3_5": 134,
    "TEST": 0,
    "TextInput1": 118,
    "TextInput2": 106,
    "TextInput3": 119,
    "Title_DataCard1": 21,
    "Title_DataCard2": 71,
    "Title1": 114,
    "Title3": 128,
    "Title5": 10
  },
  "ResourcesJsonIndices": {
    "Image-BKIM logo_clean": 1,
    "Image-BKIM logo_clean_white": 2,
    "Image-SampleImage": 0
  },
  "RuleScreenIdWithoutScreen": {},
  "TemplateVersions": {},
  "VolatileProperties": {
    "AnalysisLoadTime": 1.1073042,
    "ControlCount": {
      "button": 4,
      "dropdown": 1,
      "form": 2,
      "gallery": 4,
      "galleryTemplate": 4,
      "group": 3,
      "htmlViewer": 1,
      "icon": 4,
      "image": 6,
      "label": 64,
      "rectangle": 9,
      "screen": 5,
      "text": 17,
      "typedDataCard": 14
    },
    "DeserializationLoadTime": 2.3004548
  },
  "WasLocalDatabaseReferencesEmpty": true
}